{"nome": "nome_do_usuario", "timestamp": "AAAA-MM-DD HH-MM-SS.MMM", "cpf": "cpf_do_usuario", "id": "420728565", "wallet": 76, "produtos": [{"valor": 10, "quantidade": 1, "nome": "nome_do_produto"}], "email": "email_do_usuario"}{"nome": "nome_do_usuario", "timestamp": "AAAA-MM-DD HH-MM-SS.MMM", "cpf": "cpf_do_usuario", "id": "420728565", "wallet": 76, "produtos": [{"valor": 10, "quantidade": 1, "nome": "nome_do_produto"}], "email": "email_do_usuario"}{"nome": "Michael Michael", "cpf": "110.558.284-20", "id": "420728565", "wallet": 2444080, "produtos": [{"valor": 685, "quantidade": 3568, "nome": "hfhf"}], "email": ""}{"nome": "Michael Michael", "cpf": "110.558.284-20", "id": "420728565", "wallet": 60, "produtos": [{"valor": 12, "quantidade": 5, "nome": "vj"}], "email": ""}{"nome": "Michael Michael", "cpf": "110.558.284-20", "id": "420728565", "wallet": 40, "produtos": [{"valor": 8, "quantidade": 5, "nome": "ghh"}], "email": ""}{"nome": "Michael Michael", "cpf": "110.558.284-20", "id": "420728565", "wallet": 3936, "produtos": [{"valor": 6, "quantidade": 656, "nome": "jjf"}], "email": ""}{"nome": "Michael Michael", "cpf": "110.558.284-20", "id": "420728565", "wallet": 5590, "produtos": [{"valor": 65, "quantidade": 86, "nome": "fhg"}], "email": ""}{"nome": "Michael Michael", "cpf": "110.558.284-20", "id": "420728565", "wallet": 9230, "produtos": [{"valor": 65, "quantidade": 86, "nome": "fhg"}, {"valor": 56, "quantidade": 65, "nome": "hyf"}], "email": ""}{"nome": "Michael Michael", "cpf": "110.558.284-20", "id": "420728565", "wallet": 9510, "produtos": [{"valor": 65, "quantidade": 86, "nome": "fhg"}, {"valor": 56, "quantidade": 65, "nome": "hyf"}, {"valor": 56, "quantidade": 5, "nome": "dh"}], "email": ""}{"nome": "Michael Michael", "cpf": "110.558.284-20", "id": "420728565", "wallet": 9900, "produtos": [{"valor": 65, "quantidade": 86, "nome": "fhg"}, {"valor": 56, "quantidade": 65, "nome": "hyf"}, {"valor": 56, "quantidade": 5, "nome": "dh"}, {"valor": 6, "quantidade": 65, "nome": "ru"}], "email": ""}